farfetchd/__init__.py
farfetchd/__version__.py
farfetchd/_config.py
farfetchd/_farfetchd.py
farfetchd/base.py
farfetchd/decorators.py
farfetchd/registry.py
farfetchd/resources.py
farfetchd/serialization.py
farfetchd/defs/__init__.py
farfetchd/defs/berries.py
farfetchd/defs/contests.py
farfetchd/defs/encounters.py
farfetchd/defs/evolution.py
farfetchd/defs/games.py
farfetchd/defs/items.py
farfetchd/defs/locations.py
farfetchd/defs/machines.py
farfetchd/defs/moves.py
farfetchd/defs/pokemon.py
farfetchd/defs/utility.py
farfetchd/models/__init__.py
farfetchd/models/berries.py
farfetchd/models/contests.py
farfetchd/models/encounters.py
farfetchd/models/evolution.py
farfetchd/models/games.py
farfetchd/models/generic.py
farfetchd/models/items.py
farfetchd/models/locations.py
farfetchd/models/machines.py
farfetchd/models/moves.py
farfetchd/models/pokemon.py
farfetchd/models/utility.py
farfetchd/resolvers/__init__.py
farfetchd/resolvers/memory.py
farfetchd/resolvers/network.py
farfetchd/resolvers/resolver.py
farfetchd-0.0.1.dist-info/licenses/LICENSE
farfetchd-0.0.1.dist-info/METADATA
farfetchd-0.0.1.dist-info/WHEEL
farfetchd-0.0.1.dist-info/top_level.txt
farfetchd-0.0.1.dist-info/RECORD
